easydict/__init__.py
easydict-1.12.dist-info/LICENSE
easydict-1.12.dist-info/METADATA
easydict-1.12.dist-info/WHEEL
easydict-1.12.dist-info/top_level.txt
easydict-1.12.dist-info/RECORD
