Metadata-Version: 2.1
Name: easydict
Version: 1.12
Summary: Access dict values as attributes (works recursively).
Home-page: https://github.com/makinacorpus/easydict
Download-URL: http://pypi.python.org/pypi/easydict/
Author: Mathieu Leplatre
Author-email: mathieu.leplatre@makina-corpus.com
License: LGPL-3.0
Keywords: Tools
Classifier: Topic :: Utilities
Classifier: Natural Language :: English
Classifier: Operating System :: OS Independent
Classifier: Intended Audience :: Developers
Classifier: Development Status :: 5 - Production/Stable
Classifier: License :: OSI Approved :: GNU Lesser General Public License v3 (LGPLv3)
Classifier: Programming Language :: Python :: 2.5
Classifier: Programming Language :: Python :: 3.6
License-File: LICENSE
